{
    "object": {
        "request": {
            "id": "37b062b7-0e1d-4197-8194-c61be12d4e66",
            "body": "ewoJInR5cGUiOiJGb3JiaWRkZW5UeXBlIiwKCSJjb21tZW50IjogIlNob3VsZCBiZSByZWZ1c2VkLCBidXQgbm8gc2NvcGUgaW4gQUNMIHNvIHdpbGwgZ2V0IGFjY2VwdGVkIgp9",
            "isBase64Encoded": true,
            "headers": {
                "content-length": "102",
                "x-forwarded-proto": "https",
                "postman-token": "ac3e341e-66c1-4925-b23e-0601bba7fe71",
                "x-forwarded-port": "443",
                "x-forwarded-for": "73.189.108.108",
                "accept": "*/*",
                "x-amzn-trace-id": "Root=1-5c39235f-3da3fdfe3887efa2e0a4b515",
                "x-api-key": "testapp",
                "host": "testuser.dev.yodata.io",
                "content-type": "application/json",
                "cache-control": "no-cache",
                "accept-encoding": "gzip, deflate",
                "user-agent": "PostmanRuntime/7.6.0"
            }
        },
        "instrument": "https://testapp.dev.yodata.io/profile/card#me",
        "stage": "request",
        "hasData": true,
        "contentType": "application/json",
        "object": {
            "type": "ForbiddenType",
            "comment": "Should be refused"
        }
    },
    "scope": {
        "PublicDataOnly": {
            "effect": "Deny",
            "condition": {
                "object.type": "ForbiddenType"
            }
        }
    }
}